README.txt
setup.cfg
setup.py
docs/HISTORY.txt
docs/INSTALL.txt
docs/LICENSE.GPL
docs/LICENSE.txt
quintagroup/__init__.py
quintagroup.portlet.cumulus.egg-info/PKG-INFO
quintagroup.portlet.cumulus.egg-info/SOURCES.txt
quintagroup.portlet.cumulus.egg-info/dependency_links.txt
quintagroup.portlet.cumulus.egg-info/entry_points.txt
quintagroup.portlet.cumulus.egg-info/namespace_packages.txt
quintagroup.portlet.cumulus.egg-info/not-zip-safe
quintagroup.portlet.cumulus.egg-info/requires.txt
quintagroup.portlet.cumulus.egg-info/top_level.txt
quintagroup/portlet/__init__.py
quintagroup/portlet/cumulus/__init__.py
quintagroup/portlet/cumulus/blog.py
quintagroup/portlet/cumulus/catalog.py
quintagroup/portlet/cumulus/configure.zcml
quintagroup/portlet/cumulus/cumulusportlet.pt
quintagroup/portlet/cumulus/cumulusportlet.py
quintagroup/portlet/cumulus/interfaces.py
quintagroup/portlet/cumulus/swfobject.js
quintagroup/portlet/cumulus/tagcloud.swf
quintagroup/portlet/cumulus/version.txt
quintagroup/portlet/cumulus/locales/quintagroup.portlet.cumulus.pot
quintagroup/portlet/cumulus/profiles/default/metadata.xml
quintagroup/portlet/cumulus/profiles/default/portlets.xml
quintagroup/portlet/cumulus/tests/__init__.py
quintagroup/portlet/cumulus/tests/base.py
quintagroup/portlet/cumulus/tests/test_portlet.py