Metadata-Version: 1.0
Name: quintagroup.portlet.cumulus
Version: 1.2
Summary: A tag cloud portlet that rotates tags in 3D using a Flash movie
Home-page: http://svn.quintagroup.com/products/quintagroup.portlet.cumulus
Author: Quintagroup
Author-email: support@quintagroup.com
License: GPL
Keywords: plone portlet flash tag cloud
Platform: UNKNOWN
Classifier: Framework :: Plone
Classifier: Programming Language :: Python
Classifier: Topic :: Software Development :: Libraries :: Python Modules
